{
  "success": true,
  "meta": { "at": 1592754266101, "page_size": 1 },
  "data": [
    {
      "id": 1000542,
      "abbr": "FOM",
      "description": "Fomo3D is a decentralized, trustless blockchain game.",
      "name": "FomoThreeD",
      "num": 1,
      "total_supply": 80000000000,
      "trx_num": 1000000,
      "url": "https://fomo3d.games/",
      "owner_address": "4134f1b9c19cf40f565661697eb47b0090ac779507",
      "start_time": 1534348821000,
      "end_time": 1924876800000
    }
  ]
}
